winq2dl.py
winq2dl-2.0.4.data/scripts/winq2dl.py
winq2dl-2.0.4.dist-info/METADATA
winq2dl-2.0.4.dist-info/WHEEL
winq2dl-2.0.4.dist-info/top_level.txt
winq2dl-2.0.4.dist-info/RECORD
