Metadata-Version: 2.1
Name: winq2dl
Version: 2.0.4
Summary: A Python wrapper for the Windows API designed for drawing.
Home-page: https://github.com/AquaQuokka/winq2dl
Author: AquaQuokka
License: BSD-3-Clause
Requires-Dist: pywin32 ==306
